vape_base_extension/BaseExtension.py
vape_base_extension/__about__.py
vape_base_extension/__init__.py
vape_base_extension-1.1.2.dist-info/METADATA
vape_base_extension-1.1.2.dist-info/WHEEL
vape_base_extension-1.1.2.dist-info/licenses/LICENSE
vape_base_extension-1.1.2.dist-info/RECORD
