Metadata-Version: 2.1
Name: vape_base_extension
Version: 1.1.2
Summary: VAP-E's base extension python package
Project-URL: Documentation, https://github.com/AlanBridgeman/VAP-E_Extensions_Base-Extension-Python#readme
Project-URL: Issues, https://github.com/AlanBridgeman/VAP-E_Extensions_Base-Extension-Python/issues
Project-URL: Source, https://github.com/AlanBridgeman/VAP-E_Extensions_Base-Extension-Python
Author-email: Alan Bridgeman <alan@alanbridgeman.ca>
License-Expression: MIT
License-File: LICENSE
Classifier: Development Status :: 4 - Beta
Classifier: Programming Language :: Python
Classifier: Programming Language :: Python :: 3.7
Classifier: Programming Language :: Python :: 3.8
Classifier: Programming Language :: Python :: 3.9
Classifier: Programming Language :: Python :: 3.10
Classifier: Programming Language :: Python :: 3.11
Classifier: Programming Language :: Python :: Implementation :: CPython
Classifier: Programming Language :: Python :: Implementation :: PyPy
Requires-Python: >=3.7
